{
  "id": 2024020258,
  "season": 20242025,
  "gameType": 2,
  "limitedScoring": false,
  "gameDate": "2024-11-14",
  "venue": {
    "default": "Canadian Tire Centre"
  },
  "venueLocation": {
    "default": "Ottawa"
  },
  "startTimeUTC": "2024-11-15T00:00:00Z",
  "easternUTCOffset": "-05:00",
  "venueUTCOffset": "-05:00",
  "venueTimezone": "US/Eastern",
  "periodDescriptor": {
    "number": 4,
    "periodType": "OT",
    "maxRegulationPeriods": 3
  },
  "tvBroadcasts": [
    {
      "id": 230,
      "market": "H",
      "countryCode": "CA",
      "network": "RDS2",
      "sequenceNumber": 133
    },
    {
      "id": 294,
      "market": "H",
      "countryCode": "CA",
      "network": "TSN5",
      "sequenceNumber": 135
    },
    {
      "id": 322,
      "market": "A",
      "countryCode": "US",
      "network": "NBCSP",
      "sequenceNumber": 380
    }
  ],
  "gameState": "OFF",
  "gameScheduleState": "OK",
  "awayTeam": {
    "id": 4,
    "commonName": {
      "default": "Flyers"
    },
    "abbrev": "PHI",
    "placeName": {
      "default": "Philadelphia",
      "fr": "Philadelphie"
    },
    "placeNameWithPreposition": {
      "default": "Philadelphia",
      "fr": "de Philadelphie"
    },
    "score": 5,
    "sog": 19,
    "logo": "https://assets.nhle.com/logos/nhl/svg/PHI_light.svg",
    "darkLogo": "https://assets.nhle.com/logos/nhl/svg/PHI_dark.svg"
  },
  "homeTeam": {
    "id": 9,
    "commonName": {
      "default": "Senators",
      "fr": "S\u00e9nateurs"
    },
    "abbrev": "OTT",
    "placeName": {
      "default": "Ottawa"
    },
    "placeNameWithPreposition": {
      "default": "Ottawa",
      "fr": "d'Ottawa"
    },
    "score": 4,
    "sog": 37,
    "logo": "https://assets.nhle.com/logos/nhl/svg/OTT_light.svg",
    "darkLogo": "https://assets.nhle.com/logos/nhl/svg/OTT_dark.svg"
  },
  "shootoutInUse": true,
  "maxPeriods": 5,
  "regPeriods": 3,
  "otInUse": true,
  "tiesInUse": false,
  "summary": {
    "scoring": [
      {
        "periodDescriptor": {
          "number": 1,
          "periodType": "REG",
          "maxRegulationPeriods": 3
        },
        "goals": [
          {
            "situationCode": "1551",
            "eventId": 186,
            "strength": "ev",
            "playerId": 8477948,
            "firstName": {
              "default": "Travis"
            },
            "lastName": {
              "default": "Sanheim"
            },
            "name": {
              "default": "T. Sanheim"
            },
            "teamAbbrev": {
              "default": "PHI"
            },
            "headshot": "https://assets.nhle.com/mugs/nhl/20242025/PHI/8477948.png",
            "highlightClipSharingUrl": "https://nhl.com/video/phi-ott-sanheim-scores-goal-against-linus-ullmark-6364726012112",
            "highlightClipSharingUrlFr": "https://nhl.com/fr/video/phi-ott-sanheim-marque-un-but-contre-linus-ullmark-6364725446112",
            "highlightClip": 6364726012112,
            "highlightClipFr": 6364725446112,
            "discreteClip": 6364724559112,
            "discreteClipFr": 6364725445112,
            "goalsToDate": 4,
            "awayScore": 1,
            "homeScore": 0,
            "leadingTeamAbbrev": {
              "default": "PHI"
            },
            "timeInPeriod": "02:31",
            "shotType": "slap",
            "goalModifier": "none",
            "assists": [
              {
                "playerId": 8482126,
                "firstName": {
                  "default": "Emil"
                },
                "lastName": {
                  "default": "Andrae"
                },
                "name": {
                  "default": "E. Andrae"
                },
                "assistsToDate": 3,
                "sweaterNumber": 36
              },
              {
                "playerId": 8477903,
                "firstName": {
                  "default": "Garnet"
                },
                "lastName": {
                  "default": "Hathaway"
                },
                "name": {
                  "default": "G. Hathaway"
                },
                "assistsToDate": 5,
                "sweaterNumber": 19
              }
            ],
            "pptReplayUrl": "https://wsr.nhle.com/sprites/20242025/2024020258/ev186.json",
            "homeTeamDefendingSide": "left",
            "isHome": false
          },
          {
            "situationCode": "1551",
            "eventId": 230,
            "strength": "ev",
            "playerId": 8480801,
            "firstName": {
              "default": "Brady"
            },
            "lastName": {
              "default": "Tkachuk"
            },
            "name": {
              "default": "B. Tkachuk"
            },
            "teamAbbrev": {
              "default": "OTT"
            },
            "headshot": "https://assets.nhle.com/mugs/nhl/20242025/OTT/8480801.png",
            "highlightClipSharingUrl": "https://nhl.com/video/phi-ott-tkachuk-scores-goal-against-ivan-fedotov-6364727008112",
            "highlightClipSharingUrlFr": "https://nhl.com/fr/video/phi-ott-tkachuk-marque-un-but-contre-ivan-fedotov-6364726302112",
            "highlightClip": 6364727008112,
            "highlightClipFr": 6364726302112,
            "discreteClip": 6364726498112,
            "discreteClipFr": 6364724566112,
            "goalsToDate": 9,
            "awayScore": 1,
            "homeScore": 1,
            "timeInPeriod": "06:02",
            "shotType": "wrist",
            "goalModifier": "none",
            "assists": [
              {
                "playerId": 8480064,
                "firstName": {
                  "default": "Josh"
                },
                "lastName": {
                  "default": "Norris"
                },
                "name": {
                  "default": "J. Norris"
                },
                "assistsToDate": 5,
                "sweaterNumber": 9
              },
              {
                "playerId": 8474612,
                "firstName": {
                  "default": "Travis"
                },
                "lastName": {
                  "default": "Hamonic"
                },
                "name": {
                  "default": "T. Hamonic"
                },
                "assistsToDate": 1,
                "sweaterNumber": 23
              }
            ],
            "pptReplayUrl": "https://wsr.nhle.com/sprites/20242025/2024020258/ev230.json",
            "homeTeamDefendingSide": "left",
            "isHome": true
          }
        ]
      },
      {
        "periodDescriptor": {
          "number": 2,
          "periodType": "REG",
          "maxRegulationPeriods": 3
        },
        "goals": [
          {
            "situationCode": "1451",
            "eventId": 727,
            "strength": "pp",
            "playerId": 8480208,
            "firstName": {
              "default": "Drake"
            },
            "lastName": {
              "default": "Batherson"
            },
            "name": {
              "default": "D. Batherson"
            },
            "teamAbbrev": {
              "default": "OTT"
            },
            "headshot": "https://assets.nhle.com/mugs/nhl/20242025/OTT/8480208.png",
            "highlightClipSharingUrl": "https://nhl.com/video/phi-ott-batherson-scores-ppg-against-ivan-fedotov-6364728456112",
            "highlightClipSharingUrlFr": "https://nhl.com/fr/video/phi-ott-batherson-marque-un-but-en-a-n-contre-ivan-fedotov-6364728938112",
            "highlightClip": 6364728456112,
            "highlightClipFr": 6364728938112,
            "discreteClip": 6364728248112,
            "discreteClipFr": 6364728826112,
            "goalsToDate": 7,
            "awayScore": 1,
            "homeScore": 2,
            "leadingTeamAbbrev": {
              "default": "OTT"
            },
            "timeInPeriod": "08:41",
            "shotType": "snap",
            "goalModifier": "none",
            "assists": [
              {
                "playerId": 8482116,
                "firstName": {
                  "default": "Tim"
                },
                "lastName": {
                  "default": "St\u00fctzle"
                },
                "name": {
                  "default": "T. St\u00fctzle"
                },
                "assistsToDate": 14,
                "sweaterNumber": 18
              },
              {
                "playerId": 8482105,
                "firstName": {
                  "default": "Jake"
                },
                "lastName": {
                  "default": "Sanderson"
                },
                "name": {
                  "default": "J. Sanderson"
                },
                "assistsToDate": 9,
                "sweaterNumber": 85
              }
            ],
            "pptReplayUrl": "https://wsr.nhle.com/sprites/20242025/2024020258/ev727.json",
            "homeTeamDefendingSide": "right",
            "isHome": true
          },
          {
            "situationCode": "1551",
            "eventId": 141,
            "strength": "ev",
            "playerId": 8478439,
            "firstName": {
              "default": "Travis"
            },
            "lastName": {
              "default": "Konecny"
            },
            "name": {
              "default": "T. Konecny"
            },
            "teamAbbrev": {
              "default": "PHI"
            },
            "headshot": "https://assets.nhle.com/mugs/nhl/20242025/PHI/8478439.png",
            "highlightClipSharingUrl": "https://nhl.com/video/phi-ott-konecny-scores-goal-against-linus-ullmark-6364727597112",
            "highlightClipSharingUrlFr": "https://nhl.com/fr/video/phi-ott-konecny-marque-un-but-contre-linus-ullmark-6364728180112",
            "highlightClip": 6364727597112,
            "highlightClipFr": 6364728180112,
            "discreteClip": 6364729632112,
            "discreteClipFr": 6364729635112,
            "goalsToDate": 9,
            "awayScore": 2,
            "homeScore": 2,
            "timeInPeriod": "18:48",
            "shotType": "snap",
            "goalModifier": "none",
            "assists": [
              {
                "playerId": 8480220,
                "firstName": {
                  "default": "Noah"
                },
                "lastName": {
                  "default": "Cates"
                },
                "name": {
                  "default": "N. Cates"
                },
                "assistsToDate": 2,
                "sweaterNumber": 27
              },
              {
                "playerId": 8476372,
                "firstName": {
                  "default": "Nick"
                },
                "lastName": {
                  "default": "Seeler"
                },
                "name": {
                  "default": "N. Seeler"
                },
                "assistsToDate": 4,
                "sweaterNumber": 24
              }
            ],
            "pptReplayUrl": "https://wsr.nhle.com/sprites/20242025/2024020258/ev141.json",
            "homeTeamDefendingSide": "right",
            "isHome": false
          }
        ]
      },
      {
        "periodDescriptor": {
          "number": 3,
          "periodType": "REG",
          "maxRegulationPeriods": 3
        },
        "goals": [
          {
            "situationCode": "1551",
            "eventId": 917,
            "strength": "ev",
            "playerId": 8480064,
            "firstName": {
              "default": "Josh"
            },
            "lastName": {
              "default": "Norris"
            },
            "name": {
              "default": "J. Norris"
            },
            "teamAbbrev": {
              "default": "OTT"
            },
            "headshot": "https://assets.nhle.com/mugs/nhl/20242025/OTT/8480064.png",
            "highlightClipSharingUrl": "https://nhl.com/video/phi-ott-norris-scores-goal-against-ivan-fedotov-6364730042112",
            "highlightClipSharingUrlFr": "https://nhl.com/fr/video/phi-ott-norris-marque-un-but-contre-ivan-fedotov-6364729956112",
            "highlightClip": 6364730042112,
            "highlightClipFr": 6364729956112,
            "discreteClip": 6364728304112,
            "discreteClipFr": 6364728904112,
            "goalsToDate": 7,
            "awayScore": 2,
            "homeScore": 3,
            "leadingTeamAbbrev": {
              "default": "OTT"
            },
            "timeInPeriod": "04:27",
            "shotType": "wrist",
            "goalModifier": "none",
            "assists": [
              {
                "playerId": 8478469,
                "firstName": {
                  "default": "Thomas"
                },
                "lastName": {
                  "default": "Chabot"
                },
                "name": {
                  "default": "T. Chabot"
                },
                "assistsToDate": 9,
                "sweaterNumber": 72
              },
              {
                "playerId": 8482092,
                "firstName": {
                  "default": "Ridly"
                },
                "lastName": {
                  "default": "Greig"
                },
                "name": {
                  "default": "R. Greig"
                },
                "assistsToDate": 1,
                "sweaterNumber": 71
              }
            ],
            "pptReplayUrl": "https://wsr.nhle.com/sprites/20242025/2024020258/ev917.json",
            "homeTeamDefendingSide": "left",
            "isHome": true
          },
          {
            "situationCode": "1451",
            "eventId": 987,
            "strength": "pp",
            "playerId": 8478874,
            "firstName": {
              "default": "Adam"
            },
            "lastName": {
              "default": "Gaudette"
            },
            "name": {
              "default": "A. Gaudette"
            },
            "teamAbbrev": {
              "default": "OTT"
            },
            "headshot": "https://assets.nhle.com/mugs/nhl/20242025/OTT/8478874.png",
            "highlightClipSharingUrl": "https://nhl.com/video/phi-ott-gaudette-scores-ppg-against-ivan-fedotov-6364729018112",
            "highlightClipSharingUrlFr": "https://nhl.com/fr/video/phi-ott-gaudette-marque-un-but-en-a-n-contre-ivan-fedotov-6364729490112",
            "highlightClip": 6364729018112,
            "highlightClipFr": 6364729490112,
            "discreteClip": 6364730161112,
            "discreteClipFr": 6364730358112,
            "goalsToDate": 7,
            "awayScore": 2,
            "homeScore": 4,
            "leadingTeamAbbrev": {
              "default": "OTT"
            },
            "timeInPeriod": "10:05",
            "shotType": "backhand",
            "goalModifier": "none",
            "assists": [
              {
                "playerId": 8478469,
                "firstName": {
                  "default": "Thomas"
                },
                "lastName": {
                  "default": "Chabot"
                },
                "name": {
                  "default": "T. Chabot"
                },
                "assistsToDate": 10,
                "sweaterNumber": 72
              },
              {
                "playerId": 8482092,
                "firstName": {
                  "default": "Ridly"
                },
                "lastName": {
                  "default": "Greig"
                },
                "name": {
                  "default": "R. Greig"
                },
                "assistsToDate": 2,
                "sweaterNumber": 71
              }
            ],
            "pptReplayUrl": "https://wsr.nhle.com/sprites/20242025/2024020258/ev987.json",
            "homeTeamDefendingSide": "left",
            "isHome": true
          },
          {
            "situationCode": "1551",
            "eventId": 1000,
            "strength": "ev",
            "playerId": 8478409,
            "firstName": {
              "default": "Anthony"
            },
            "lastName": {
              "default": "Richard"
            },
            "name": {
              "default": "A. Richard"
            },
            "teamAbbrev": {
              "default": "PHI"
            },
            "headshot": "https://assets.nhle.com/mugs/nhl/20242025/PHI/8478409.png",
            "highlightClipSharingUrl": "https://nhl.com/video/phi-ott-richard-scores-goal-against-linus-ullmark-6364730852112",
            "highlightClipSharingUrlFr": "https://nhl.com/fr/video/phi-ott-richard-marque-un-but-contre-linus-ullmark-6364730559112",
            "highlightClip": 6364730852112,
            "highlightClipFr": 6364730559112,
            "discreteClip": 6364731160112,
            "discreteClipFr": 6364731163112,
            "goalsToDate": 2,
            "awayScore": 3,
            "homeScore": 4,
            "leadingTeamAbbrev": {
              "default": "OTT"
            },
            "timeInPeriod": "10:42",
            "shotType": "snap",
            "goalModifier": "none",
            "assists": [
              {
                "playerId": 8481553,
                "firstName": {
                  "default": "Bobby"
                },
                "lastName": {
                  "default": "Brink"
                },
                "name": {
                  "default": "B. Brink"
                },
                "assistsToDate": 5,
                "sweaterNumber": 10
              },
              {
                "playerId": 8481178,
                "firstName": {
                  "default": "Egor",
                  "cs": "Jegor",
                  "de": "Yegor",
                  "es": "Yegor",
                  "fi": "Jegor",
                  "sk": "Jegor",
                  "sv": "Yegor"
                },
                "lastName": {
                  "default": "Zamula"
                },
                "name": {
                  "default": "E. Zamula",
                  "cs": "J. Zamula",
                  "de": "Y. Zamula",
                  "es": "Y. Zamula",
                  "fi": "J. Zamula",
                  "sk": "J. Zamula",
                  "sv": "Y. Zamula"
                },
                "assistsToDate": 4,
                "sweaterNumber": 5
              }
            ],
            "pptReplayUrl": "https://wsr.nhle.com/sprites/20242025/2024020258/ev1000.json",
            "homeTeamDefendingSide": "left",
            "isHome": false
          },
          {
            "situationCode": "1551",
            "eventId": 654,
            "strength": "ev",
            "playerId": 8481553,
            "firstName": {
              "default": "Bobby"
            },
            "lastName": {
              "default": "Brink"
            },
            "name": {
              "default": "B. Brink"
            },
            "teamAbbrev": {
              "default": "PHI"
            },
            "headshot": "https://assets.nhle.com/mugs/nhl/20242025/PHI/8481553.png",
            "highlightClipSharingUrl": "https://nhl.com/video/",
            "highlightClip": 6364729987112,
            "discreteClip": 6364730271112,
            "discreteClipFr": 6364730772112,
            "goalsToDate": 3,
            "awayScore": 4,
            "homeScore": 4,
            "timeInPeriod": "12:45",
            "shotType": "deflected",
            "goalModifier": "none",
            "assists": [
              {
                "playerId": 8478409,
                "firstName": {
                  "default": "Anthony"
                },
                "lastName": {
                  "default": "Richard"
                },
                "name": {
                  "default": "A. Richard"
                },
                "assistsToDate": 2,
                "sweaterNumber": 90
              },
              {
                "playerId": 8477948,
                "firstName": {
                  "default": "Travis"
                },
                "lastName": {
                  "default": "Sanheim"
                },
                "name": {
                  "default": "T. Sanheim"
                },
                "assistsToDate": 4,
                "sweaterNumber": 6
              }
            ],
            "pptReplayUrl": "https://wsr.nhle.com/sprites/20242025/2024020258/ev654.json",
            "homeTeamDefendingSide": "left",
            "isHome": false
          }
        ]
      },
      {
        "periodDescriptor": {
          "number": 4,
          "periodType": "OT",
          "maxRegulationPeriods": 3
        },
        "goals": [
          {
            "situationCode": "1331",
            "eventId": 1158,
            "strength": "ev",
            "playerId": 8484387,
            "firstName": {
              "default": "Matvei",
              "cs": "Matvej",
              "sk": "Matvej"
            },
            "lastName": {
              "default": "Michkov",
              "cs": "Mi\u010dkov",
              "fi": "Mitshkov",
              "sk": "Mi\u010dkov"
            },
            "name": {
              "default": "M. Michkov",
              "cs": "M. Mi\u010dkov",
              "fi": "M. Mitshkov",
              "sk": "M. Mi\u010dkov"
            },
            "teamAbbrev": {
              "default": "PHI"
            },
            "headshot": "https://assets.nhle.com/mugs/nhl/20242025/PHI/8484387.png",
            "highlightClipSharingUrl": "https://nhl.com/video/phi-ott-michkov-scores-goal-against-linus-ullmark-6364730399112",
            "highlightClipSharingUrlFr": "https://nhl.com/fr/video/phi-ott-michkov-marque-un-but-contre-linus-ullmark-6364730404112",
            "highlightClip": 6364730399112,
            "highlightClipFr": 6364730404112,
            "discreteClip": 6364729920112,
            "discreteClipFr": 6364730981112,
            "goalsToDate": 6,
            "awayScore": 5,
            "homeScore": 4,
            "leadingTeamAbbrev": {
              "default": "PHI"
            },
            "timeInPeriod": "04:05",
            "shotType": "wrist",
            "goalModifier": "none",
            "assists": [
              {
                "playerId": 8478439,
                "firstName": {
                  "default": "Travis"
                },
                "lastName": {
                  "default": "Konecny"
                },
                "name": {
                  "default": "T. Konecny"
                },
                "assistsToDate": 10,
                "sweaterNumber": 11
              },
              {
                "playerId": 8477948,
                "firstName": {
                  "default": "Travis"
                },
                "lastName": {
                  "default": "Sanheim"
                },
                "name": {
                  "default": "T. Sanheim"
                },
                "assistsToDate": 5,
                "sweaterNumber": 6
              }
            ],
            "pptReplayUrl": "https://wsr.nhle.com/sprites/20242025/2024020258/ev1158.json",
            "homeTeamDefendingSide": "right",
            "isHome": false
          }
        ]
      }
    ],
    "shootout": [],
    "threeStars": [
      {
        "star": 1,
        "playerId": 8484387,
        "teamAbbrev": "PHI",
        "headshot": "https://assets.nhle.com/mugs/nhl/20242025/PHI/8484387.png",
        "name": {
          "default": "M. Michkov",
          "cs": "M. Mi\u010dkov",
          "fi": "M. Mitshkov",
          "sk": "M. Mi\u010dkov"
        },
        "sweaterNo": 39,
        "position": "R",
        "goals": 1,
        "assists": 0,
        "points": 1
      },
      {
        "star": 2,
        "playerId": 8480064,
        "teamAbbrev": "OTT",
        "headshot": "https://assets.nhle.com/mugs/nhl/20242025/OTT/8480064.png",
        "name": {
          "default": "J. Norris"
        },
        "sweaterNo": 9,
        "position": "C",
        "goals": 1,
        "assists": 1,
        "points": 2
      },
      {
        "star": 3,
        "playerId": 8477948,
        "teamAbbrev": "PHI",
        "headshot": "https://assets.nhle.com/mugs/nhl/20242025/PHI/8477948.png",
        "name": {
          "default": "T. Sanheim"
        },
        "sweaterNo": 6,
        "position": "D",
        "goals": 1,
        "assists": 2,
        "points": 3
      }
    ],
    "penalties": [
      {
        "periodDescriptor": {
          "number": 1,
          "periodType": "REG",
          "maxRegulationPeriods": 3
        },
        "penalties": [
          {
            "timeInPeriod": "12:32",
            "type": "MIN",
            "duration": 2,
            "committedByPlayer": {
              "default": "T. Chabot"
            },
            "teamAbbrev": {
              "default": "OTT"
            },
            "drawnBy": {
              "default": "G. Hathaway"
            },
            "descKey": "holding"
          },
          {
            "timeInPeriod": "17:56",
            "type": "MIN",
            "duration": 2,
            "committedByPlayer": {
              "default": "M. Michkov",
              "cs": "M. Mi\u010dkov",
              "fi": "M. Mitshkov",
              "sk": "M. Mi\u010dkov"
            },
            "teamAbbrev": {
              "default": "PHI"
            },
            "drawnBy": {
              "default": "B. Tkachuk"
            },
            "descKey": "cross-checking"
          }
        ]
      },
      {
        "periodDescriptor": {
          "number": 2,
          "periodType": "REG",
          "maxRegulationPeriods": 3
        },
        "penalties": [
          {
            "timeInPeriod": "04:09",
            "type": "MIN",
            "duration": 2,
            "committedByPlayer": {
              "default": "T. Sanheim"
            },
            "teamAbbrev": {
              "default": "PHI"
            },
            "drawnBy": {
              "default": "J. Norris"
            },
            "descKey": "cross-checking"
          },
          {
            "timeInPeriod": "08:16",
            "type": "MIN",
            "duration": 2,
            "committedByPlayer": {
              "default": "J. Farabee"
            },
            "teamAbbrev": {
              "default": "PHI"
            },
            "drawnBy": {
              "default": "N. Jensen"
            },
            "descKey": "high-sticking"
          },
          {
            "timeInPeriod": "09:57",
            "type": "MIN",
            "duration": 2,
            "committedByPlayer": {
              "default": "R. Ristolainen"
            },
            "teamAbbrev": {
              "default": "PHI"
            },
            "drawnBy": {
              "default": "Z. MacEwen",
              "cs": "Z. Macewen",
              "de": "Z. Macewen",
              "es": "Z. Macewen",
              "fi": "Z. Macewen",
              "sk": "Z. Macewen",
              "sv": "Z. Macewen"
            },
            "descKey": "holding"
          },
          {
            "timeInPeriod": "15:45",
            "type": "MIN",
            "duration": 2,
            "committedByPlayer": {
              "default": "J. Norris"
            },
            "teamAbbrev": {
              "default": "OTT"
            },
            "drawnBy": {
              "default": "M. Michkov",
              "cs": "M. Mi\u010dkov",
              "fi": "M. Mitshkov",
              "sk": "M. Mi\u010dkov"
            },
            "descKey": "tripping"
          },
          {
            "timeInPeriod": "16:22",
            "type": "MIN",
            "duration": 2,
            "committedByPlayer": {
              "default": "T. Foerster"
            },
            "teamAbbrev": {
              "default": "PHI"
            },
            "drawnBy": {
              "default": "T. Chabot"
            },
            "descKey": "tripping"
          }
        ]
      },
      {
        "periodDescriptor": {
          "number": 3,
          "periodType": "REG",
          "maxRegulationPeriods": 3
        },
        "penalties": [
          {
            "timeInPeriod": "08:37",
            "type": "MIN",
            "duration": 2,
            "committedByPlayer": {
              "default": "E. Andrae"
            },
            "teamAbbrev": {
              "default": "PHI"
            },
            "drawnBy": {
              "default": "D. Batherson"
            },
            "descKey": "slashing"
          }
        ]
      },
      {
        "periodDescriptor": {
          "number": 4,
          "periodType": "OT",
          "maxRegulationPeriods": 3
        },
        "penalties": []
      }
    ]
  },
  "clock": {
    "timeRemaining": "00:55",
    "secondsRemaining": 55,
    "running": false,
    "inIntermission": false
  }
}